atlasapi/__init__.py
atlasapi/alerts.py
atlasapi/api_keys.py
atlasapi/atlas.py
atlasapi/atlas_types.py
atlasapi/atlas_users.py
atlasapi/cloud_backup.py
atlasapi/clusters.py
atlasapi/errors.py
atlasapi/events.py
atlasapi/events_event_types.py
atlasapi/invoices_pydantic.py
atlasapi/lib.py
atlasapi/logs.py
atlasapi/maintenance_window.py
atlasapi/measurements.py
atlasapi/network.py
atlasapi/organizations.py
atlasapi/projects.py
atlasapi/serverless_pydantic.py
atlasapi/settings.py
atlasapi/specs.py
atlasapi/teams.py
atlasapi/whitelist.py
atlascli/__init__.py
atlascli/atlaserrors.py
atlascli/atlaskey.py
atlascli/cli.py
atlascli/listcommand.py
atlasapi-2.0.11.dist-info/LICENSE
atlasapi-2.0.11.dist-info/METADATA
atlasapi-2.0.11.dist-info/WHEEL
atlasapi-2.0.11.dist-info/entry_points.txt
atlasapi-2.0.11.dist-info/top_level.txt
atlasapi-2.0.11.dist-info/RECORD
