Metadata-Version: 2.1
Name: atlasapi
Version: 2.0.11
Summary: Expose MongoDB Atlas Cloud provider APIs
Home-page: https://github.com/mgmonteleone/python-atlasapi
Author: Matthew G. Monteleone
Author-email: mgm@mgm.dev
License: Apache License 2.0
Keywords: atlas,mongo,mongodb,cloud,api
Classifier: Development Status :: 5 - Production/Stable
Classifier: Intended Audience :: Developers
Classifier: License :: OSI Approved :: Apache Software License
Classifier: Operating System :: OS Independent
Classifier: Programming Language :: Python :: 3 :: Only
Classifier: Programming Language :: Python :: 3.7
Classifier: Programming Language :: Python :: 3.8
Classifier: Programming Language :: Python :: 3.9
Requires-Python: >=3.7
License-File: LICENSE
Requires-Dist: requests
Requires-Dist: python-dateutil
Requires-Dist: isodate
Requires-Dist: future
Requires-Dist: pytz
Requires-Dist: coolname
Requires-Dist: humanfriendly
Requires-Dist: nose
